{
  "settings": {
    "migrated": 2,
    "iconPacksPath": ".obsidian/plugins/obsidian-icon-folder/icons",
    "fontSize": 16,
    "emojiStyle": "none",
    "iconColor": "#2455a3",
    "recentlyUsedIcons": [
      "TiDatabaseShare",
      "FabChessRook",
      "FabCss3",
      "FabConnectdevelop",
      "FabDraft2digital"
    ],
    "recentlyUsedIconsSize": 5,
    "rules": [],
    "extraMargin": {
      "top": 0,
      "right": 4,
      "bottom": 0,
      "left": 0
    },
    "iconInTabsEnabled": false
  },
  "00-MOC": "FabCreativeCommonsNd",
  "01-Diary": "FabAirbnb",
  "02-Reading": "FabBootstrap",
  "03-Projects": "FabCcApplePay",
  "04-笔记": "FabCottonBureau",
  "04-笔记/01-效率生活": {
    "iconName": "FabAngellist",
    "inheritanceIcon": "FabAdversal"
  },
  "05-课程": "FabContao",
  "06-Cards": "FabCloudversify",
  "07-Archives": "FabDashcube",
  "08-Assets": "FabDraft2digital",
  "09-Templates": "FabConnectdevelop",
  "10-资料收集": "FabCss3",
  "04-笔记/02-编程/01-编程语言": "FabChessRook",
  "04-笔记/02-编程/02-数据格式": "TiDatabaseShare"
}